eclipsetorch/__init__.py
eclipsetorch/model.py
eclipsetorch/training.py
eclipsetorch/utils.py
eclipsetorch-0.0.2.dist-info/LICENSE
eclipsetorch-0.0.2.dist-info/METADATA
eclipsetorch-0.0.2.dist-info/WHEEL
eclipsetorch-0.0.2.dist-info/top_level.txt
eclipsetorch-0.0.2.dist-info/RECORD
