Metadata-Version: 2.1
Name: eclipsetorch
Version: 0.0.2
Summary: A custom set of tools to make making models a bit easier
Author: Matthew Sanchez
Author-email: xxspicymelonxx@gmail.com
Classifier: Programming Language :: Python :: 3
Classifier: License :: OSI Approved :: MIT License
Classifier: Operating System :: OS Independent
Requires-Python: >=3.10
License-File: LICENSE
Requires-Dist: torch
Requires-Dist: torchvision
Requires-Dist: transformers
Requires-Dist: pillow
Requires-Dist: numpy
